optymus/__about__.py
optymus/__init__.py
optymus/benchmark/__init__.py
optymus/benchmark/_comparison.py
optymus/benchmark/_obj_functions.py
optymus/benchmark/_topological_domain.py
optymus/benchmark/utils/_domain_functions.py
optymus/methods/__init__.py
optymus/methods/adaptive/__init__.py
optymus/methods/adaptive/_adagrad.py
optymus/methods/adaptive/_adam.py
optymus/methods/adaptive/_adamax.py
optymus/methods/adaptive/_rmsprop.py
optymus/methods/adaptive/_yogi.py
optymus/methods/first_order/__init__.py
optymus/methods/first_order/_bfgs.py
optymus/methods/first_order/_conjugate_gradient.py
optymus/methods/first_order/_lbfgs.py
optymus/methods/first_order/_steepest_descent.py
optymus/methods/population/__init__.py
optymus/methods/population/_differential_evolution.py
optymus/methods/population/_particle_swarm.py
optymus/methods/second_order/__init__.py
optymus/methods/second_order/_newton_raphson.py
optymus/methods/stochastic/__init__.py
optymus/methods/stochastic/_cmaes.py
optymus/methods/stochastic/_cross_entropy.py
optymus/methods/stochastic/_sgd.py
optymus/methods/stochastic/_simulated_anneling.py
optymus/methods/topological/__init__.py
optymus/methods/topological/_polymesher.py
optymus/methods/utils/__init__.py
optymus/methods/utils/_base.py
optymus/methods/zero_order/__init__.py
optymus/methods/zero_order/_oc.py
optymus/methods/zero_order/_powell.py
optymus/methods/zero_order/_univariate.py
optymus/optimizer/_optimizer.py
optymus/optimizer/utils/report.py
optymus/plots/__init__.py
optymus/plots/_plots.py
optymus/search/__init__.py
optymus/search/_search.py
optymus-0.1.10.dist-info/licenses/LICENSE
optymus-0.1.10.dist-info/METADATA
optymus-0.1.10.dist-info/WHEEL
optymus-0.1.10.dist-info/top_level.txt
optymus-0.1.10.dist-info/RECORD
