Metadata-Version: 2.4
Name: optymus
Version: 0.1.10
Summary: Optimization methods in Python
Project-URL: Homepage, https://github.com/quant-sci/optymus
Project-URL: Bug Tracker, https://github.com/quant-sci/optymus/issues
Requires-Python: >=3.12
License-File: LICENSE
Requires-Dist: plotly==5.24.1
Requires-Dist: nbformat>=4.2.0
Requires-Dist: jax>=0.4.28
Requires-Dist: jaxlib>=0.4.28
Requires-Dist: tqdm>=4.66.4
Requires-Dist: pandas>=2.2
Requires-Dist: numpy==1.26.4
Requires-Dist: matplotlib>=3.9.0
Requires-Dist: seaborn>=0.13.2
Requires-Dist: scikit-learn>=1.5.0
Provides-Extra: dev
Requires-Dist: pytest~=8.2; extra == "dev"
Requires-Dist: black~=24.4; extra == "dev"
Requires-Dist: ruff~=0.4; extra == "dev"
Provides-Extra: testing
Requires-Dist: plotly==5.24.1; extra == "testing"
Requires-Dist: nbformat>=4.2.0; extra == "testing"
Requires-Dist: jax>=0.4.28; extra == "testing"
Requires-Dist: jaxlib>=0.4.28; extra == "testing"
Requires-Dist: tqdm>=4.66.4; extra == "testing"
Requires-Dist: pandas>=2.2; extra == "testing"
Requires-Dist: numpy==1.26.4; extra == "testing"
Requires-Dist: matplotlib>=3.9.0; extra == "testing"
Requires-Dist: seaborn>=0.13.2; extra == "testing"
Requires-Dist: scikit-learn>=1.5.0; extra == "testing"
Requires-Dist: ipykernel; extra == "testing"
Provides-Extra: docs
Requires-Dist: pydata-sphinx-theme==0.15.2; extra == "docs"
Requires-Dist: sphinx_design==0.5.0; extra == "docs"
Requires-Dist: sphinx_togglebutton==0.3.2; extra == "docs"
Requires-Dist: sphinxcontrib.youtube==1.4.1; extra == "docs"
Requires-Dist: sphinx_copybutton==0.5.2; extra == "docs"
Requires-Dist: myst_parser==3.0.1; extra == "docs"
Requires-Dist: nbsphinx==0.9.4; extra == "docs"
Requires-Dist: ipython==8.25.0; extra == "docs"
Dynamic: license-file
